{
  "violations": [
    {
      "excerpt": "name too short",
      "type": "too_short"
    }
  ],
  "has_violations": true,
  "num_comments": 3,
  "package_author": "utkinis",
  "decision": {
    "merged": true,
    "closed_by": null,
    "merged_by": "giordano",
    "time_to_decision_days": 4
  },
  "pr_number": 112026,
  "package_name": "Chmy",
  "discussion": [
    {
      "influence": 3,
      "author": "utkinis",
      "author_association": "NONE",
      "text": "Hello, is it possible to have the package registered with the current name, i.e. Chmy? It is being used under this name by several collaborators internally, and was introduced at JuliaCon. I don't think it is visually too similar to Why.\r\n[noblock]",
      "stance": "pro_merge"
    },
    {
      "influence": 1,
      "author": "luraess",
      "author_association": "NONE",
      "text": "Manual merge would be appreciated, as 3 days passed 🙏 [noblock]",
      "stance": "unrelated"
    }
  ],
  "wrapper_info": {
    "is_wrapper": false,
    "wrapped_library": null
  },
  "slack_mentioned": false,
  "justifications": [
    "minimum_length_satisfied",
    "established_name"
  ],
  "related_prs": []
}