{
  "created_at": "2019-10-08T17:46:06Z",
  "review_comments": [],
  "state": "closed",
  "author": "JuliaRegistrator",
  "closed_by": "DilumAluthge",
  "merged_at": null,
  "pr_number": 4184,
  "comments": [
    {
      "id": "MDEyOklzc3VlQ29tbWVudDU0Mjg5NTg0MQ==",
      "author": {
        "login": "fredrikekre"
      },
      "authorAssociation": "MEMBER",
      "body": "Please add (at least)\r\n```\r\n[compat]\r\njulia = \"1\"\r\n```\r\nto your project file and retrigger the bot.",
      "createdAt": "2019-10-16T21:18:21Z",
      "includesCreatedEdit": false,
      "isMinimized": false,
      "minimizedReason": "",
      "reactionGroups": [],
      "url": "https://github.com/JuliaRegistries/General/pull/4184#issuecomment-542895841",
      "viewerDidAuthor": false
    },
    {
      "id": "MDEyOklzc3VlQ29tbWVudDU0Njg0OTE0Nw==",
      "author": {
        "login": "fredrikekre"
      },
      "authorAssociation": "MEMBER",
      "body": "bump @emmettgb",
      "createdAt": "2019-10-28T08:49:53Z",
      "includesCreatedEdit": false,
      "isMinimized": false,
      "minimizedReason": "",
      "reactionGroups": [],
      "url": "https://github.com/JuliaRegistries/General/pull/4184#issuecomment-546849147",
      "viewerDidAuthor": false
    },
    {
      "id": "MDEyOklzc3VlQ29tbWVudDU0ODE0OTMwNg==",
      "author": {
        "login": "DilumAluthge"
      },
      "authorAssociation": "MEMBER",
      "body": "Closing in favor of https://github.com/JuliaRegistries/General/pull/4551",
      "createdAt": "2019-10-30T23:04:47Z",
      "includesCreatedEdit": false,
      "isMinimized": false,
      "minimizedReason": "",
      "reactionGroups": [],
      "url": "https://github.com/JuliaRegistries/General/pull/4184#issuecomment-548149306",
      "viewerDidAuthor": false
    }
  ],
  "merged_by": null,
  "body": "- Registering package: Lathe\n- Repository: https://github.com/emmettgb/Lathe.jl\n- Created by: @emmettgb\n- Version: v0.0.1\n- Commit: 7610adafdc95fa2dc6ccd6b29f6f4fa3190e4624\n- Git reference: master",
  "package_name": "Lathe",
  "closed_at": "2019-10-30T23:04:47Z",
  "title": "New package: Lathe v0.0.1"
}